kcolors/__init__.py
kcolors/__main__.py
kcolors/irefs.py
kcolors/refs.py
kcolors/utils.py
kcolors/src/__init__.py
kcolors/src/colors.py
kcolors-0.1.1.8.dist-info/LICENSE
kcolors-0.1.1.8.dist-info/METADATA
kcolors-0.1.1.8.dist-info/WHEEL
kcolors-0.1.1.8.dist-info/top_level.txt
kcolors-0.1.1.8.dist-info/RECORD
