Metadata-Version: 2.1
Name: kcolors
Version: 0.1.1.8
Summary: Automatic/Static ANSI colors for python
Home-page: https://github.com/kokaito-git/kcolors
Author: kokaito
Author-email: kokaito.git@gmail.com
Classifier: Programming Language :: Python :: 3
Classifier: License :: OSI Approved :: MIT License
Classifier: Operating System :: OS Independent
Classifier: Operating System :: Microsoft :: Windows
Classifier: Operating System :: MacOS
Classifier: Operating System :: POSIX :: Linux
License-File: LICENSE
